MANIFEST.in
setup.py
ds1054z/__init__.py
ds1054z/cli.py
ds1054z/discovery.py
ds1054z.egg-info/PKG-INFO
ds1054z.egg-info/SOURCES.txt
ds1054z.egg-info/dependency_links.txt
ds1054z.egg-info/entry_points.txt
ds1054z.egg-info/requires.txt
ds1054z.egg-info/top_level.txt
ds1054z.egg-info/zip-safe
ds1054z/resources/overlay.png