Metadata-Version: 1.1
Name: ds1054z
Version: 0.3.5
Summary: Python package and software for the Rigol DS1054Z oscilloscope.
Home-page: https://github.com/pklaus/ds1054z
Author: Philipp Klaus
Author-email: philipp.l.klaus@web.de
License: GPL
Keywords: Rigol Oscilloscope DS1054Z
Platform: any
Classifier: Development Status :: 4 - Beta
Classifier: Operating System :: OS Independent
Classifier: License :: OSI Approved :: GNU General Public License v3 or later (GPLv3+)
Classifier: Programming Language :: Python
Classifier: Programming Language :: Python :: 3
Classifier: Topic :: Scientific/Engineering :: Visualization
Classifier: Topic :: Scientific/Engineering
Classifier: Topic :: System :: Hardware :: Hardware Drivers
Classifier: Intended Audience :: Science/Research
